pynb_live-0.1.1.dist-info/DESCRIPTION.rst
pynb_live-0.1.1.dist-info/METADATA
pynb_live-0.1.1.dist-info/RECORD
pynb_live-0.1.1.dist-info/WHEEL
pynb_live-0.1.1.dist-info/dependency_links.txt
pynb_live-0.1.1.dist-info/entry_points.txt
pynb_live-0.1.1.dist-info/metadata.json
pynb_live-0.1.1.dist-info/top_level.txt
pynb_livereload/__init__.py
pynb_livereload/pynb_livereload.py
