Metadata-Version: 2.0
Name: pynb-live
Version: 0.1.1
Summary: UNKNOWN
Home-page: UNKNOWN
Author: Alexander C. Mueller
Author-email: mail@alexcmueller.de
License: MIT
Platform: UNKNOWN
Classifier: Development Status :: 3 - Alpha
Classifier: Intended Audience :: Developers
Classifier: Intended Audience :: Science/Research
Classifier: Intended Audience :: System Administrators
Classifier: License :: OSI Approved :: MIT License
Classifier: Programming Language :: Python :: 3
Requires-Python: >=3.4
Requires-Dist: pynb
